Tool.py
einsztestlib/__init__.py
einsztestlib/szlibone.py
einsztestlib-1.0.0.dist-info/METADATA
einsztestlib-1.0.0.dist-info/RECORD
einsztestlib-1.0.0.dist-info/WHEEL
einsztestlib-1.0.0.dist-info/top_level.txt
