Metadata-Version: 2.1
Name: einsztestlib
Version: 1.0.0
Summary: this is a niubi lib
Home-page: https://github.com/wangshunzi/Python_code
Author: sz
Author-email: 18856426129ik@gmail.com
License: UNKNOWN
Platform: UNKNOWN
